myfunctions_diana11d/__init__.py
myfunctions_diana11d/math.py
myfunctions_diana11d-0.0.5.dist-info/METADATA
myfunctions_diana11d-0.0.5.dist-info/WHEEL
myfunctions_diana11d-0.0.5.dist-info/top_level.txt
myfunctions_diana11d-0.0.5.dist-info/RECORD
