Metadata-Version: 2.1
Name: myfunctions-diana11d
Version: 0.0.5
Summary: A description of your package
Home-page: https://github.com/Diana11d
Author: Diana Dauletkerey
Author-email: ddauletkerey02@gmail.com
License: MIT
Platform: UNKNOWN
Classifier: Programming Language :: Python :: 3
Classifier: License :: OSI Approved :: MIT License
Classifier: Operating System :: OS Independent
Requires-Python: >=3.6
Requires-Dist: os
